{
  "parent": "minecraft:recipes/root",
  "rewards": {
    "recipes": [
      "atomiccomponents:raw_titanium_block"
    ]
  },
  "criteria": {
    "has_raw": {
      "trigger": "minecraft:inventory_changed",
      "conditions": {
        "items": [
          {
            "tag": "forge:raw/titanium"
          }
        ]
      }
    },
    "has_the_recipe": {
      "trigger": "minecraft:recipe_unlocked",
      "conditions": {
        "recipe": "atomiccomponents:raw_titanium_block"
      }
    }
  },
  "requirements": [
    [
      "has_raw",
      "has_the_recipe"
    ]
  ]
}